Metadata-Version: 2.1
Name: faradaydreams
Version: 0.0.3
Summary: Faraday Rotation Recovery using Convex Optimization
Home-page: https://github.com/Luke-Pratley/Faraday-Dreams
Author: Luke Pratley
Author-email: luke.pratley@gmail.com
License: UNKNOWN
Platform: UNKNOWN
Classifier: Programming Language :: Python :: 3
Classifier: License :: OSI Approved :: GNU General Public License v3 (GPLv3)
Classifier: Operating System :: OS Independent
Requires-Python: >=3.8
